fraudguard/__init__.py
fraudguard/core/__init__.py
fraudguard/core/base.py
fraudguard/core/config.py
fraudguard/core/exceptions.py
fraudguard/deployment/__init__.py
fraudguard/deployment/api_server.py
fraudguard/deployment/batch_processor.py
fraudguard/features/__init__.py
fraudguard/features/behavioral.py
fraudguard/features/temporal.py
fraudguard/features/transaction.py
fraudguard/features/velocity.py
fraudguard/models/__init__.py
fraudguard/models/anomaly_model.py
fraudguard/models/base_model.py
fraudguard/models/ensemble_model.py
fraudguard/models/random_forest_model.py
fraudguard/models/xgboost_model.py
fraudguard/pipeline/__init__.py
fraudguard/pipeline/feature_pipeline.py
fraudguard/pipeline/fraud_detection_pipeline.py
fraudguard/pipeline/model_orchestrator.py
fraudguard/pipeline/scoring_engine.py
fraudguard/utils/__init__.py
fraudguard/utils/metrics.py
fraudguard/utils/preprocessing.py
fraudguard/utils/validation.py
fraudguard-0.1.0.dist-info/licenses/LICENSE
fraudguard-0.1.0.dist-info/METADATA
fraudguard-0.1.0.dist-info/WHEEL
fraudguard-0.1.0.dist-info/entry_points.txt
fraudguard-0.1.0.dist-info/top_level.txt
fraudguard-0.1.0.dist-info/RECORD
