Metadata-Version: 2.4
Name: fraudguard
Version: 0.1.0
Summary: A modular Python package for financial fraud detection using machine learning
Author-email: Advait Dharmadhikari <advaituni@gmail.com>
License: MIT License
Project-URL: Homepage, https://github.com/advait27/fraudguard
Project-URL: Documentation, https://fraudguard.readthedocs.io
Project-URL: Repository, https://github.com/advait27/fraudguard.git
Project-URL: Bug Tracker, https://github.com/advait27/fraudguard/issues
Keywords: fraud,detection,machine-learning,finance,security
Classifier: Development Status :: 4 - Beta
Classifier: Intended Audience :: Financial and Insurance Industry
Classifier: Topic :: Office/Business :: Financial
Classifier: Topic :: Scientific/Engineering :: Artificial Intelligence
Classifier: License :: OSI Approved :: MIT License
Classifier: Programming Language :: Python :: 3
Classifier: Programming Language :: Python :: 3.8
Classifier: Programming Language :: Python :: 3.9
Classifier: Programming Language :: Python :: 3.10
Classifier: Programming Language :: Python :: 3.11
Requires-Python: >=3.8
License-File: LICENSE
Requires-Dist: pandas>=1.3.0
Requires-Dist: numpy>=1.20.0
Requires-Dist: scikit-learn>=1.0.0
Requires-Dist: xgboost>=1.5.0
Requires-Dist: lightgbm>=3.2.0
Requires-Dist: imbalanced-learn>=0.8.0
Requires-Dist: shap>=0.40.0
Requires-Dist: fastapi>=0.70.0
Requires-Dist: uvicorn>=0.15.0
Requires-Dist: pydantic>=1.8.0
Requires-Dist: pyyaml>=5.4.0
Requires-Dist: joblib>=1.1.0
Requires-Dist: matplotlib>=3.5.0
Requires-Dist: seaborn>=0.11.0
Provides-Extra: dev
Requires-Dist: pytest>=6.0; extra == "dev"
Requires-Dist: pytest-cov>=2.12.0; extra == "dev"
Requires-Dist: black>=21.0.0; extra == "dev"
Requires-Dist: flake8>=3.9.0; extra == "dev"
Requires-Dist: mypy>=0.910; extra == "dev"
Requires-Dist: pre-commit>=2.15.0; extra == "dev"
Provides-Extra: docs
Requires-Dist: sphinx>=4.0.0; extra == "docs"
Requires-Dist: sphinx-rtd-theme>=0.5.0; extra == "docs"
Provides-Extra: deployment
Requires-Dist: docker>=5.0.0; extra == "deployment"
Requires-Dist: kubernetes>=18.20.0; extra == "deployment"
Requires-Dist: redis>=3.5.0; extra == "deployment"
Requires-Dist: celery>=5.2.0; extra == "deployment"
Dynamic: license-file
Dynamic: requires-python
